Metadata-Version: 2.1
Name: odoo-addon-stock_request_picking_type
Version: 17.0.1.0.0.5
Requires-Python: >=3.10
Requires-Dist: odoo-addon-stock_request>=17.0dev,<17.1dev
Requires-Dist: odoo>=17.0a,<17.1dev
Summary: Add Stock Requests to the Inventory App
Home-page: https://github.com/OCA/stock-logistics-request
License: LGPL-3
Author: Open Source Integrators, Odoo Community Association (OCA)
Author-email: support@odoo-community.org
Classifier: Programming Language :: Python
Classifier: Framework :: Odoo
Classifier: Framework :: Odoo :: 17.0
Classifier: License :: OSI Approved :: GNU Lesser General Public License v3 (LGPLv3)
Classifier: Development Status :: 4 - Beta
